{"id":"46734293","premium":false,"billing_type":{"id":"standard","name":"Стандарт"},"relations":[],"name":"Разработчик (JS, C#)","insider_interview":null,"response_letter_required":false,"area":{"id":"1","name":"Москва","url":"https://api.hh.ru/areas/1?host=hh.ru"},"salary":null,"type":{"id":"open","name":"Открытая"},"address":{"city":"Москва","street":"Замоскворецкая линия","building":"метро Автозаводская","description":null,"lat":55.707182,"lng":37.657646,"raw":"Москва, Замоскворецкая линия, метро Автозаводская","metro":null,"metro_stations":[]},"allow_messages":true,"site":{"id":"hh","name":"hh.ru"},"experience":{"id":"between1And3","name":"От 1 года до 3 лет"},"schedule":{"id":"fullDay","name":"Полный день"},"employment":{"id":"full","name":"Полная занятость"},"department":null,"contacts":null,"description":"<p><strong>Приглашаем в наш коллектив специалистов с различным опытом и объемом знаний, желанием активно совершенствовать профессиональные знания, готовых к ответственной работе на больших и интересных проектах.</strong></p> <p><strong>Рабочие задачи</strong></p> <p>• Создание и развитие проектных решений</p> <p>• Автоматизация бизнес-процессов и реализация интеграционных решений</p> <p>• Верификация проектных задач и участие в постановке задач</p> <p>• Решение проектных задач во взаимодействии с проектной командой</p> <p>• Аудит качества разрабатываемого кода бизнес приложений</p> <p>• Участие в построении процессов разработки</p> <p><strong>Требования к соискателю</strong></p> <p>• Знание принципов web-разработки на стеке: C#, ASP.NET, JavaScript, IIS, Ext.js и Vue.js / React</p> <p>• Опыт работы с реляционными базами данных (T-SQL), ORM Entity Fremework</p> <p>• Навыки работы с системами контроля версий Apache Subversion (SVN), Git</p> <p>• Знание CSS, PL/SQL, TeamCity, Jira</p> <p>• Методология Agile, Scrum</p> <p>• Нацеленность на результат, аккуратность, пунктуальность, ответственность</p> <p>• Способность и желание быстрого обучения</p> <p>• Приветствуется знание английского языка</p> <p><strong>Условия работы</strong></p> <p>• Интересные проекты уровня Enterprise</p> <p>• Поддержка и практическое обучение со стороны специалистов высокой компетенции</p> <p>• Профессиональное развитие: сертификация, конференции, внутренние курсы</p> <p>• Демократичный корпоративный климат, молодой и дружный коллектив</p> <p>• Уровень зарплаты по итогам собеседования</p> <p>• Увеличение ставки по практическим результатам</p> <p>• Базовый рабочий график 5/2 с гибким началом рабочего дня и рабочего процесса. Возможно удаленно.</p> <p>• У нас можно поболеть пару дней без больничного листа</p> <p>• Испытательный срок 0-3 месяца</p> <ul> </ul>","branded_description":null,"vacancy_constructor_template":null,"key_skills":[{"name":"JavaScript"},{"name":"C#"},{"name":"ASP.NET"},{"name":"MySQL"},{"name":"Git"},{"name":"HTML"},{"name":"SVN"},{"name":"Ext JS"},{"name":".NET Framework"},{"name":"Terrasoft CRM"},{"name":"Atlassian Jira"},{"name":"Agile Project Management"},{"name":"Creatio"},{"name":"TeamCity"},{"name":"CSS"},{"name":"IIS"},{"name":"Scrum"}],"accept_handicapped":false,"accept_kids":false,"archived":false,"response_url":null,"specializations":[{"id":"1.221","name":"Программирование, Разработка","profarea_id":"1","profarea_name":"Информационные технологии, интернет, телеком"}],"code":"Р-20-06","hidden":false,"quick_responses_allowed":false,"driver_license_types":[],"accept_incomplete_resumes":false,"employer":{"id":"4421340","name":"ГК Интеграция","url":"https://api.hh.ru/employers/4421340?host=hh.ru","alternate_url":"https://hh.ru/employer/4421340","logo_urls":{"original":"https://hhcdn.ru/employer-logo-original/806239.png","90":"https://hhcdn.ru/employer-logo/3665843.png","240":"https://hhcdn.ru/employer-logo/3665844.png"},"vacancies_url":"https://api.hh.ru/vacancies?employer_id=4421340&host=hh.ru","trusted":true},"published_at":"2021-09-21T17:41:45+0300","created_at":"2021-09-21T17:41:45+0300","negotiations_url":null,"suitable_resumes_url":null,"apply_alternate_url":"https://hh.ru/applicant/vacancy_response?vacancyId=46734293","has_test":false,"test":null,"alternate_url":"https://hh.ru/vacancy/46734293","working_days":[],"working_time_intervals":[],"working_time_modes":[],"accept_temporary":false}