{"id":"47313531","premium":false,"billing_type":{"id":"standard","name":"Стандарт"},"relations":[],"name":"Project manager","insider_interview":null,"response_letter_required":false,"area":{"id":"1","name":"Москва","url":"https://api.hh.ru/areas/1?host=hh.ru"},"salary":null,"type":{"id":"open","name":"Открытая"},"address":{"city":"Москва","street":"Поклонная улица","building":"3","description":null,"lat":55.736174,"lng":37.533185,"raw":"Москва, Поклонная улица, 3","metro":null,"metro_stations":[]},"allow_messages":true,"site":{"id":"hh","name":"hh.ru"},"experience":{"id":"between1And3","name":"От 1 года до 3 лет"},"schedule":{"id":"fullDay","name":"Полный день"},"employment":{"id":"full","name":"Полная занятость"},"department":null,"contacts":null,"description":"<p>«СберСпасибо»- крупнейшая банковская программа лояльности, созданная для клиентов ПАО Сбербанк.</p> <p><em>Мы ищем специалиста на стыке системного и бизнес - анализа, который будет отвечать за аналитику в продукте Впечатлений на нашем сайте и в Мобильном приложении.</em></p> <p><strong>Обязанности:</strong></p> <ul> <li>Разбираться в бизнес-процессах, проектировать и анализировать архитектуру системы и клиентский путь;</li> <li>Готовить и уточнять детальные требования со стороны PO и иных внутренних заказчиков (разработка, SAS, процессинг и тд) для разработки;</li> <li>Ставить задачи на команду разработки, принимать задачу как заказчик при поддержке PO и тестировщика;</li> <li>Формировать спринты, сопровождать релизный цикл;</li> <li>Разрабатывать и согласовывать проектную и техническую документацию, концепции, тех задания.</li> </ul> <p><em>Если вы умеете задавать вопросы, которые помогают добраться до сути и умеете самостоятельно находить нужную информацию. Если любите «закапываться» в технические или бизнес-дебри, всё систематизировать и вернуться с понятными требованиями. Пишете так, чтобы текст легко понимали и разработчики и заказчики. И если ваш девиз по жизни – проактивность, то с удовольствием ждем в нашей команде. </em></p> <strong>Требования:</strong> <ul> <li>Высшее техническое или математическое образование;</li> <li>Опыт составления и согласования бизнес и системных требований и проектной документации; (опыт в разработке сайтов и МП будет плюсом);</li> <li>Опыт работы с административными панелями сайта (администрирование, размещение контента)</li> <li>Умение проводить экспресс оценку требований;</li> <li>Уверенные знания и опыт работы с продуктами Jira, Confluence, Microsoft Office (Excel, Visio, Word);</li> <li>Опыт работы с описанием API и процессов (sequence diagram, XSD, JSON-schema), знание UML, BPMN будет преимуществом;</li> <li>Опыт интеграции технических систем;</li> <li>Знание принципов REST/SOAP взаимодействий, очередей сообщений;</li> <li>Плюсом будет: знание SQL или разработки на любом языке программирования, знание основ html, css, адаптивной вёрстки, успешный опыт интеграции двух систем между собой , опыт оценки эффекта от внедрения новых задач, знание принципов работы систем контроля версий, например, Git;</li> <li>Ответственность;</li> <li>Развитые коммуникативные навыки;</li> <li>Внимательность к деталям;</li> <li>Лидерство;</li> <li>Умение отстаивать свою позицию.</li> </ul> <strong>Условия:</strong> <ul> <li>Социальный пакет ДМС и НС;</li> <li>Офис: ст. метро Кутузовская;</li> <li>Конкурентная заработная плата;</li> <li>Премия;</li> <li>Льготные условия для потребительского и ипотечного кредитования.</li> </ul>","branded_description":null,"vacancy_constructor_template":null,"key_skills":[{"name":"Git"},{"name":"SQL"},{"name":"HTML"},{"name":"BPMN"},{"name":"Atlassian Jira"},{"name":"MS Office"},{"name":"Figma"},{"name":"Miro"}],"accept_handicapped":false,"accept_kids":false,"archived":false,"response_url":null,"specializations":[{"id":"1.25","name":"Аналитик","profarea_id":"1","profarea_name":"Информационные технологии, интернет, телеком"}],"code":null,"hidden":false,"quick_responses_allowed":false,"driver_license_types":[],"accept_incomplete_resumes":false,"employer":{"id":"4315301","name":"СберСпасибо","url":"https://api.hh.ru/employers/4315301?host=hh.ru","alternate_url":"https://hh.ru/employer/4315301","logo_urls":{"240":"https://hhcdn.ru/employer-logo/3809408.png","90":"https://hhcdn.ru/employer-logo/3809407.png","original":"https://hhcdn.ru/employer-logo-original/842133.png"},"vacancies_url":"https://api.hh.ru/vacancies?employer_id=4315301&host=hh.ru","trusted":true},"published_at":"2021-09-08T15:11:49+0300","created_at":"2021-09-08T15:11:49+0300","negotiations_url":null,"suitable_resumes_url":null,"apply_alternate_url":"https://hh.ru/applicant/vacancy_response?vacancyId=47313531","has_test":false,"test":null,"alternate_url":"https://hh.ru/vacancy/47313531","working_days":[],"working_time_intervals":[],"working_time_modes":[],"accept_temporary":false}