{"id":"47419515","premium":false,"billing_type":{"id":"standard","name":"Стандарт"},"relations":[],"name":"Администратор в студию лазерной эпиляции","insider_interview":null,"response_letter_required":false,"area":{"id":"1","name":"Москва","url":"https://api.hh.ru/areas/1?host=hh.ru"},"salary":{"from":50000,"to":null,"currency":"RUR","gross":false},"type":{"id":"open","name":"Открытая"},"address":null,"allow_messages":true,"site":{"id":"hh","name":"hh.ru"},"experience":{"id":"between1And3","name":"От 1 года до 3 лет"},"schedule":{"id":"fullDay","name":"Полный день"},"employment":{"id":"full","name":"Полная занятость"},"department":null,"contacts":null,"description":"<p>Требуемый опыт работы: от полугода.</p> <p>Полная занятость, сменный график 2/2 (обсуждается).</p> <p>Возможно временное оформление: договор услуг, подряда, ГПХ, самозанятые, ИП</p> <p><strong>РАБОТА НА СТАНЦИИ МЕТРО 1905 года.</strong></p> <p><strong>Обязанности</strong>:</p> <p>-Ведение записи клиентов на процедуры;<br />-Открытие/закрытие студии;<br />-Консультация клиентов в студии и по телефону;<br />-Работа в Ycliens<br />-Общение с клиентами в соц сетях;<br />-Встреча клиентов и создание хороших условий ожидания процедуры.</p> <p><br />Требования:<br />-Доброжелательность;<br />-Грамотная речь;<br />-Чувство такта в работе с клиентами и сотрудниками студии;<br />-Оконченное образование (не рассматриваем совмещение с учебой).<br /><br /><strong>Условия</strong>:<br />-Оклад (30.000-35.000) + премия= от 50000 рублей в месяц, выплаты два раза в месяц без задержек.<br />-Оформление по самозанятости (процент компенсируем, с третьего месяца по ТК);<br />-Обучение за счет компании;<br />-Красивая студия, комфортное рабочее место, дружная команда;<br /><strong>-График работы 2х2, с 10:00 до 22:00;</strong><br />-Бонус: для наших сотрудниц процедура лазерной эпиляции бесплатно!</p> <p>Пишите в ватсап или оставляйте отклик. Вышлю вам анкету для заполнения.</p>","branded_description":null,"vacancy_constructor_template":null,"key_skills":[{"name":"Грамотная речь"},{"name":"Работа в команде"},{"name":"Деловое общение"},{"name":"Грамотность"},{"name":"Телефонные переговоры"}],"accept_handicapped":false,"accept_kids":false,"archived":false,"response_url":null,"specializations":[{"id":"24.379","name":"Администрация","profarea_id":"24","profarea_name":"Спортивные клубы, фитнес, салоны красоты"}],"code":null,"hidden":false,"quick_responses_allowed":false,"driver_license_types":[],"accept_incomplete_resumes":false,"employer":{"id":"5673906","name":"Mona studio","url":"https://api.hh.ru/employers/5673906?host=hh.ru","alternate_url":"https://hh.ru/employer/5673906","logo_urls":{"original":"https://hhcdn.ru/employer-logo-original/892723.jpg","90":"https://hhcdn.ru/employer-logo/4011579.jpeg","240":"https://hhcdn.ru/employer-logo/4011580.jpeg"},"vacancies_url":"https://api.hh.ru/vacancies?employer_id=5673906&host=hh.ru","trusted":true},"published_at":"2021-08-26T21:20:37+0300","created_at":"2021-08-26T21:20:37+0300","negotiations_url":null,"suitable_resumes_url":null,"apply_alternate_url":"https://hh.ru/applicant/vacancy_response?vacancyId=47419515","has_test":false,"test":null,"alternate_url":"https://hh.ru/vacancy/47419515","working_days":[],"working_time_intervals":[],"working_time_modes":[],"accept_temporary":false}