{"id":"47445948","premium":false,"billing_type":{"id":"standard","name":"Стандарт"},"relations":[],"name":"Няня","insider_interview":null,"response_letter_required":false,"area":{"id":"1","name":"Москва","url":"https://api.hh.ru/areas/1?host=hh.ru"},"salary":{"from":60000,"to":null,"currency":"RUR","gross":true},"type":{"id":"open","name":"Открытая"},"address":null,"allow_messages":true,"site":{"id":"hh","name":"hh.ru"},"experience":{"id":"between3And6","name":"От 3 до 6 лет"},"schedule":{"id":"fullDay","name":"Полный день"},"employment":{"id":"full","name":"Полная занятость"},"department":null,"contacts":null,"description":"<p>Требуется няня для девочки (4 месяца)</p> <p><strong>Обязанности: </strong></p> <p>- Гулять с ребенком;</p> <p>- Приносить на кормление маме;</p> <p>- Если вы умеете готовить - это идеально;</p> <p><strong>Требования:</strong></p> <p>- Опыт работы с детками разного возраста;</p> <p>- Готовность к поездкам и командировкам (например, поехать в Сочи на месяц (проживание и перелет оплатим);</p> <p>- Любовь к детям;</p> <p>- Опыт работы от 3 лет;</p> <p><strong>Условия: </strong></p> <p>- График: 5/2;</p> <p>- Заработная плата по договоренности;</p> <p> </p> <p> </p> <ul> </ul>","branded_description":null,"vacancy_constructor_template":null,"key_skills":[{"name":"Грамотная речь"},{"name":"Мобильность"},{"name":"Умение работать в коллективе"},{"name":"Любовь к детям"},{"name":"способность анализировать проблемы, эффективно искать пути их разрешения"}],"accept_handicapped":false,"accept_kids":false,"archived":false,"response_url":null,"specializations":[{"id":"27.496","name":"Воспитатель, Гувернантка/гувернёр, Няня","profarea_id":"27","profarea_name":"Домашний персонал"},{"id":"27.533","name":"Помощник по хозяйству, Управляющий","profarea_id":"27","profarea_name":"Домашний персонал"}],"code":null,"hidden":false,"quick_responses_allowed":false,"driver_license_types":[],"accept_incomplete_resumes":false,"employer":{"id":"4807693","name":"Гогаладзе Ольга Юрьевна","url":"https://api.hh.ru/employers/4807693?host=hh.ru","alternate_url":"https://hh.ru/employer/4807693","logo_urls":{"original":"https://hhcdn.ru/employer-logo-original/799959.jpg","90":"https://hhcdn.ru/employer-logo/3640723.jpeg","240":"https://hhcdn.ru/employer-logo/3640724.jpeg"},"vacancies_url":"https://api.hh.ru/vacancies?employer_id=4807693&host=hh.ru","trusted":true},"published_at":"2021-08-27T17:01:05+0300","created_at":"2021-08-27T17:01:05+0300","negotiations_url":null,"suitable_resumes_url":null,"apply_alternate_url":"https://hh.ru/applicant/vacancy_response?vacancyId=47445948","has_test":false,"test":null,"alternate_url":"https://hh.ru/vacancy/47445948","working_days":[],"working_time_intervals":[],"working_time_modes":[],"accept_temporary":false}