{"id":"47505421","premium":false,"billing_type":{"id":"standard","name":"Стандарт"},"relations":[],"name":"Помощник юриста","insider_interview":null,"response_letter_required":false,"area":{"id":"1","name":"Москва","url":"https://api.hh.ru/areas/1?host=hh.ru"},"salary":{"from":40000,"to":60000,"currency":"RUR","gross":false},"type":{"id":"open","name":"Открытая"},"address":{"city":"Москва","street":"Лубянский проезд","building":"15с2","description":null,"lat":55.756817,"lng":37.632305,"raw":"Москва, Лубянский проезд, 15с2","metro":{"station_name":"Китай-город","line_name":"Калужско-Рижская","station_id":"6.50","line_id":"6","lat":55.756498,"lng":37.631326},"metro_stations":[{"station_name":"Китай-город","line_name":"Калужско-Рижская","station_id":"6.50","line_id":"6","lat":55.756498,"lng":37.631326},{"station_name":"Китай-город","line_name":"Таганско-Краснопресненская","station_id":"7.51","line_id":"7","lat":55.75436,"lng":37.633877}]},"allow_messages":true,"site":{"id":"hh","name":"hh.ru"},"experience":{"id":"noExperience","name":"Нет опыта"},"schedule":{"id":"fullDay","name":"Полный день"},"employment":{"id":"full","name":"Полная занятость"},"department":null,"contacts":null,"description":"<p>В юридическую компанию требуется Помощник Юриста:</p> <p><br /><strong>Профессиональные требования:</strong></p> <ul> <li>Высшее юридическое образование</li> <li>Опыт работы не обязателен</li> <li>Внимательность и грамотность</li> <li>Аналитический склад ума</li> <li>Желание расти и развиваться</li> <li>Умение грамотно излагать свои мысли</li> <li>Грамотная устная и письменная речь</li> <li>Организованность</li> <li>Ответственность, активность, инициативность</li> </ul> <p><strong>Обязанности:</strong></p> <ul> <li>Составление простых процессуальных документов (отзывы, ходатайства, возражения) и их электронная подача</li> <li>Помощь в организации и ведении судебных дел</li> <li>Консультирование клиентов по услугам компании</li> <li>Подготовка и отправка документов для регистрации юридических лиц</li> <li>Выезд в различные инстанции по поручению руководителя</li> <li>Подбор юридических адресов</li> <li>Размещение каталога на сайте</li> <li>Отслеживание картотеки арбитражных дел</li> <li>Оформление дел</li> <li>Подготовка списков</li> </ul> <p><strong>Условия:</strong></p> <ul> <li>Место работы – офис в центре Москвы с удобным расположением, ст.м. Китай-город;</li> <li>Работа в офисе пн-пт. с 10.00 до 19.00 или с 9.00 до 18.00</li> <li>Стабильная заработная плата - оклад + бонусная часть</li> <li>Официальное трудоустройство</li> <li>Испытательный срок - 2 месяца</li> <li>Перспектива карьерного и финансового роста</li> </ul>","branded_description":null,"vacancy_constructor_template":null,"key_skills":[],"accept_handicapped":false,"accept_kids":false,"archived":false,"response_url":null,"specializations":[{"id":"23.29","name":"Арбитраж","profarea_id":"23","profarea_name":"Юристы"},{"id":"23.477","name":"Договорное право","profarea_id":"23","profarea_name":"Юристы"},{"id":"23.182","name":"Начальный уровень, Мало опыта","profarea_id":"23","profarea_name":"Юристы"},{"id":"23.214","name":"Помощник","profarea_id":"23","profarea_name":"Юристы"},{"id":"23.362","name":"Юрисконсульт","profarea_id":"23","profarea_name":"Юристы"}],"code":null,"hidden":false,"quick_responses_allowed":false,"driver_license_types":[],"accept_incomplete_resumes":false,"employer":{"id":"604386","name":"ACCOUNT, Юридическая компания","url":"https://api.hh.ru/employers/604386?host=hh.ru","alternate_url":"https://hh.ru/employer/604386","logo_urls":{"240":"https://hhcdn.ru/employer-logo/3461894.png","90":"https://hhcdn.ru/employer-logo/3461893.png","original":"https://hhcdn.ru/employer-logo-original/755234.png"},"vacancies_url":"https://api.hh.ru/vacancies?employer_id=604386&host=hh.ru","trusted":true},"published_at":"2021-08-31T09:14:51+0300","created_at":"2021-08-31T09:14:51+0300","negotiations_url":null,"suitable_resumes_url":null,"apply_alternate_url":"https://hh.ru/applicant/vacancy_response?vacancyId=47505421","has_test":false,"test":null,"alternate_url":"https://hh.ru/vacancy/47505421","working_days":[],"working_time_intervals":[],"working_time_modes":[],"accept_temporary":false}