{"id":"47592452","premium":false,"billing_type":{"id":"standard","name":"Стандарт"},"relations":[],"name":"Администратор в центр красоты","insider_interview":null,"response_letter_required":false,"area":{"id":"1","name":"Москва","url":"https://api.hh.ru/areas/1?host=hh.ru"},"salary":{"from":80000,"to":85000,"currency":"RUR","gross":false},"type":{"id":"open","name":"Открытая"},"address":{"city":"Москва","street":"улица Охотный Ряд","building":"2","description":null,"lat":55.757131,"lng":37.617114,"raw":"Москва, улица Охотный Ряд, 2","metro":null,"metro_stations":[]},"allow_messages":true,"site":{"id":"hh","name":"hh.ru"},"experience":{"id":"between3And6","name":"От 3 до 6 лет"},"schedule":{"id":"fullDay","name":"Полный день"},"employment":{"id":"full","name":"Полная занятость"},"department":null,"contacts":null,"description":"<p>Если вы мечтаете построить карьеру в сфере красоты и услуг - приглашаем вас начать свой карьерный пусть с нами!</p> <p>В премиальную сеть салонов красоты и косметологии требуется Администратор</p> <p><strong>Обязанности:</strong></p> <p>- Работа с премиальными клиентами</p> <p>- Входящие звонки, консультирование и запись клиентов по всем направлениям услуг</p> <p>- Выполнения поставленных задач KPI и плана записи</p> <p>- Консультирование клиентов по услугам салона и действующих акциях</p> <p>- Встреча, консультирование и запись клиентов салона</p> <p>- Отчетность о проделанной работе, выполнение поручений руководителя подразделения</p> <p><strong>Требования:</strong></p> <ul> <li>Опыт работы администратором в салоне красоты от 3х лет</li> <li>Знание специфики салонов красоты</li> <li>Знание услуг салонов красоты</li> <li>Понимание премиального сервиса</li> <li>Грамотная письменная и устная речь</li> <li>Аккуратность, исполнительность, усидчивость, умение работать в режиме многозадачности</li> </ul> <p><strong>Личные качества:</strong></p> <ul> <li>Ответственность</li> <li>Усидчивость</li> <li>Внимание</li> <li>Доброжелательность</li> <li>Любовь к своему делу</li> <li>Желание расти и развиваться в индустрии красоты и сервиса</li> </ul> <p><strong>Условия:</strong></p> <ul> <li>График работы 2/2</li> <li>Рабочий день с 10:00 до 22:00</li> <li>Работа в самом центре Москвы – метро Охотный ряд (ТГ Модный сезон)</li> <li>Мотивация: 60 000 р. оклад + бонус дня и бонус месяца до 30.000р.</li> <li>Уровень дохода от 80.000 руб</li> <li>Обучение внутри компании, повышение квалификации</li> <li>Молодой и дружный коллектив</li> <li>Карьерный рост</li> </ul> <p><strong>Контактная информация: </strong></p> <p>Москва, улица Охотный Ряд, 2, ТГ Модный сезон, 3 этаж</p>","branded_description":null,"vacancy_constructor_template":null,"key_skills":[{"name":"Грамотная речь"},{"name":"Прием и распределение телефонных звонков"},{"name":"Пользователь ПК"},{"name":"Деловое общение"},{"name":"Консультирование"}],"accept_handicapped":false,"accept_kids":false,"archived":false,"response_url":null,"specializations":[{"id":"24.379","name":"Администрация","profarea_id":"24","profarea_name":"Спортивные клубы, фитнес, салоны красоты"},{"id":"24.380","name":"Продажи","profarea_id":"24","profarea_name":"Спортивные клубы, фитнес, салоны красоты"}],"code":null,"hidden":false,"quick_responses_allowed":false,"driver_license_types":[],"accept_incomplete_resumes":false,"employer":{"id":"1052429","name":"Legend New York Центр Красоты и Косметологии","url":"https://api.hh.ru/employers/1052429?host=hh.ru","alternate_url":"https://hh.ru/employer/1052429","logo_urls":{"240":"https://hhcdn.ru/employer-logo/3453146.jpeg","90":"https://hhcdn.ru/employer-logo/3453145.jpeg","original":"https://hhcdn.ru/employer-logo-original/753047.jpg"},"vacancies_url":"https://api.hh.ru/vacancies?employer_id=1052429&host=hh.ru","trusted":true},"published_at":"2021-09-02T13:03:52+0300","created_at":"2021-09-02T13:03:52+0300","negotiations_url":null,"suitable_resumes_url":null,"apply_alternate_url":"https://hh.ru/applicant/vacancy_response?vacancyId=47592452","has_test":false,"test":null,"alternate_url":"https://hh.ru/vacancy/47592452","working_days":[],"working_time_intervals":[],"working_time_modes":[],"accept_temporary":false}