{"id":"47647671","premium":false,"billing_type":{"id":"standard","name":"Стандарт"},"relations":[],"name":"Мастер маникюра и педикюра","insider_interview":null,"response_letter_required":false,"area":{"id":"1","name":"Москва","url":"https://api.hh.ru/areas/1?host=hh.ru"},"salary":{"from":70000,"to":130000,"currency":"RUR","gross":true},"type":{"id":"open","name":"Открытая"},"address":{"city":"Москва","street":"улица Шаболовка","building":"19","description":null,"lat":55.723491,"lng":37.611329,"raw":"Москва, улица Шаболовка, 19","metro":null,"metro_stations":[]},"allow_messages":true,"site":{"id":"hh","name":"hh.ru"},"experience":{"id":"between1And3","name":"От 1 года до 3 лет"},"schedule":{"id":"shift","name":"Сменный график"},"employment":{"id":"full","name":"Полная занятость"},"department":null,"contacts":null,"description":"<p><strong>Cesare Ponti – это современный салон красоты, сочетающий мастерство специалистов, отточенное качество каждой услуги, модные тренды и сервис премиум класса с честными ценами.</strong></p> <p><strong>CesarePonti = качество + эстетика + мода + безопасность + скорость + сервис + честность.</strong></p> <p><strong>Мечтаете развиваться в beauty-индустрии вместе с сильной командой?</strong></p> <p><strong>Получить уникальный опыт работы с настоящими профессионалами?</strong></p> <p><strong>Выбирайте вакансию по своему вкусу и звоните, пишите нам!</strong></p> <p><strong>Наши сильные стороны:</strong></p> <ol> <li>Сервис, отличный от других мест.</li> <li>Эстетика и качество в каждой мелочи.</li> <li>Элитарность.</li> <li>Работа в команде с профессионалами.</li> <li>Постоянное повышение знаний и рост.</li> <li>Серьезный подход к дезинфекции и безопасности</li> </ol> <p> </p> <p><strong>Мы за такие навыки, как:</strong></p> <ul> <li>опыт работы от 1 года</li> <li>владение техниками классического/аппаратного/пилочного маникюра и педикюра</li> <li>владение техниками покрытий</li> <li>эстетика в работе</li> <li>вовлеченность в свою профессию</li> </ul> <p> </p> <p><strong>Мы вместе будем:</strong></p> <ul> <li>влюблять гостей в наш бренд</li> <li>учиться у лучших и развивать наши умения и навыки</li> <li>работать с качественными, коллегиально выбранными брендами</li> <li>реализовывать идеи и планы компании</li> </ul> <p> </p> <p><strong>Мы дадим тебе:</strong></p> <ul> <li>работа в самом центре Москвы, 5 минут от метро Шаболовская</li> <li>максимум комфорта в работе, лучшие инструменты и бренды</li> <li>стабильную финансовую оплату: % от услуг и % от продаж (от 6000р в день).</li> <li>обучения за счет компании</li> </ul>","branded_description":null,"vacancy_constructor_template":null,"key_skills":[{"name":"Работа в команде"},{"name":"Креативность"},{"name":"Навыки межличностного общения"},{"name":"Расстановка приоритетов"}],"accept_handicapped":false,"accept_kids":false,"archived":false,"response_url":null,"specializations":[{"id":"17.334","name":"Услуги для населения","profarea_id":"17","profarea_name":"Продажи"},{"id":"24.624","name":"Ногтевой сервис","profarea_id":"24","profarea_name":"Спортивные клубы, фитнес, салоны красоты"}],"code":null,"hidden":false,"quick_responses_allowed":false,"driver_license_types":[],"accept_incomplete_resumes":true,"employer":{"id":"4311580","name":"CESARE PONTI (ИП Спиридонова Александра Ильинична)","url":"https://api.hh.ru/employers/4311580?host=hh.ru","alternate_url":"https://hh.ru/employer/4311580","logo_urls":{"original":"https://hhcdn.ru/employer-logo-original/684711.png","240":"https://hhcdn.ru/employer-logo/3179977.png","90":"https://hhcdn.ru/employer-logo/3179976.png"},"vacancies_url":"https://api.hh.ru/vacancies?employer_id=4311580&host=hh.ru","trusted":true},"published_at":"2021-09-04T12:41:57+0300","created_at":"2021-09-04T12:41:57+0300","negotiations_url":null,"suitable_resumes_url":null,"apply_alternate_url":"https://hh.ru/applicant/vacancy_response?vacancyId=47647671","has_test":false,"test":null,"alternate_url":"https://hh.ru/vacancy/47647671","working_days":[],"working_time_intervals":[],"working_time_modes":[],"accept_temporary":false}