{"id":"47679114","premium":false,"billing_type":{"id":"standard","name":"Стандарт"},"relations":[],"name":"Стикеровщик одежды ZARА на склад","insider_interview":null,"response_letter_required":false,"area":{"id":"1","name":"Москва","url":"https://api.hh.ru/areas/1?host=hh.ru"},"salary":{"from":67900,"to":116000,"currency":"RUR","gross":true},"type":{"id":"open","name":"Открытая"},"address":{"city":"Москва","street":"Никитинская улица","building":null,"description":null,"lat":55.801485,"lng":37.774822,"raw":"Москва, Никитинская улица","metro":{"station_name":"Измайловская","line_name":"Арбатско-Покровская","station_id":"3.40","line_id":"3","lat":55.787713,"lng":37.779896},"metro_stations":[{"station_name":"Измайловская","line_name":"Арбатско-Покровская","station_id":"3.40","line_id":"3","lat":55.787713,"lng":37.779896},{"station_name":"Первомайская","line_name":"Арбатско-Покровская","station_id":"3.106","line_id":"3","lat":55.794376,"lng":37.799364},{"station_name":"Тимирязевская","line_name":"Серпуховско-Тимирязевская","station_id":"9.141","line_id":"9","lat":55.81866,"lng":37.574498},{"station_name":"Щелковская","line_name":"Арбатско-Покровская","station_id":"3.159","line_id":"3","lat":55.809962,"lng":37.798261}]},"allow_messages":true,"site":{"id":"hh","name":"hh.ru"},"experience":{"id":"noExperience","name":"Нет опыта"},"schedule":{"id":"flyInFlyOut","name":"Вахтовый метод"},"employment":{"id":"full","name":"Полная занятость"},"department":null,"contacts":null,"description":"<p><strong>Работа с бесплатным проживанием и питанием.<br />Набираем сотрудников на склад.</strong></p> <p><strong>Обязанности: </strong>Упаковка и подготовка продукции к отправке.</p> <p><strong>Требования: </strong>Готовность работать вахтовым методом.</p> <p><strong>Условия:</strong></p> <ul> <li> <p>Вахта от 15 / 30 / 45 / 60 / 90 смен</p> </li> <li> <p>Рабочий график: 6/1, 7/0. Дневные и ночные смены.</p> </li> <li> <p>Смена 11 часов, 1 час обеденный перерыв.</p> </li> <li> <p>Официальное оформление.</p> </li> </ul> <p><strong>Оплата:</strong></p> <ul> <li> <p>от 52 000 до 85 000 за вахту на 30 смен,</p> </li> </ul> <ul> <li> <p>от 104 000 до 170 000 за вахту на 60 смен,</p> </li> </ul> <ul> <li> <p>от 156 000 до 255 000 за вахту на 90 смен.</p> </li> </ul> <ul> <li> <p>Выплаты 2 раза в месяц</p> </li> <li> <p>Все выплаты на Вашу личную карту (любого банка)</p> </li> <li> <p>Еженедельное авансирование.</p> </li> </ul> <p><strong>Бесплатное:</strong></p> <ul> <li> <p>Питание</p> </li> <li> <p>Проживание (есть семейные комнаты)</p> </li> <li> <p>Форма</p> </li> </ul> <p><strong>Акции:</strong></p> <ul> <li> <p>Приглашайте друзей на работу и получайте премию - 5000 руб.</p> </li> <li> <p>Оплата билета с первой вахты или на вторую до 3000 руб.</p> </li> </ul> <p><strong>Уважаемые кандидаты, вы можете уточнить все подробности вакансии или записаться на собеседование по телефону.</strong></p> <p><strong>Звоните, и мы запишем вас на собеседование!</strong></p>","branded_description":null,"vacancy_constructor_template":null,"key_skills":[],"accept_handicapped":true,"accept_kids":false,"archived":false,"response_url":null,"specializations":[{"id":"7.733","name":"Другое","profarea_id":"7","profarea_name":"Автомобильный бизнес"},{"id":"4.734","name":"Другое","profarea_id":"4","profarea_name":"Административный персонал"},{"id":"15.750","name":"Другое","profarea_id":"15","profarea_name":"Начало карьеры, студенты"},{"id":"17.751","name":"Другое","profarea_id":"17","profarea_name":"Продажи"},{"id":"29.545","name":"Комплектовщик, Укладчик-упаковщик","profarea_id":"29","profarea_name":"Рабочий персонал"},{"id":"2.737","name":"Другое","profarea_id":"2","profarea_name":"Бухгалтерия, управленческий учет, финансы предприятия"}],"code":null,"hidden":false,"quick_responses_allowed":false,"driver_license_types":[],"accept_incomplete_resumes":true,"employer":{"id":"5683314","name":"Брайт","url":"https://api.hh.ru/employers/5683314?host=hh.ru","alternate_url":"https://hh.ru/employer/5683314","logo_urls":{"240":"https://hhcdn.ru/employer-logo/3982704.png","90":"https://hhcdn.ru/employer-logo/3982703.png","original":"https://hhcdn.ru/employer-logo-original/885501.png"},"vacancies_url":"https://api.hh.ru/vacancies?employer_id=5683314&host=hh.ru","trusted":true},"published_at":"2021-09-20T12:17:23+0300","created_at":"2021-09-20T12:17:23+0300","negotiations_url":null,"suitable_resumes_url":null,"apply_alternate_url":"https://hh.ru/applicant/vacancy_response?vacancyId=47679114","has_test":false,"test":null,"alternate_url":"https://hh.ru/vacancy/47679114","working_days":[],"working_time_intervals":[],"working_time_modes":[],"accept_temporary":true}