{"id":"47763742","premium":false,"billing_type":{"id":"standard","name":"Стандарт"},"relations":[],"name":"Бариста-ученик в кофейню","insider_interview":null,"response_letter_required":false,"area":{"id":"1","name":"Москва","url":"https://api.hh.ru/areas/1?host=hh.ru"},"salary":{"from":40100,"to":55900,"currency":"RUR","gross":false},"type":{"id":"open","name":"Открытая"},"address":{"city":"Москва","street":"Центральный административный округ, Тверской район, Театральный проезд","building":null,"description":null,"lat":55.758949,"lng":37.620681,"raw":"Москва, Центральный административный округ, Тверской район, Театральный проезд","metro":{"station_name":"Лубянка","line_name":"Сокольническая","station_id":"1.66","line_id":"1","lat":55.759889,"lng":37.625336},"metro_stations":[{"station_name":"Лубянка","line_name":"Сокольническая","station_id":"1.66","line_id":"1","lat":55.759889,"lng":37.625336},{"station_name":"Марьино","line_name":"Люблинско-Дмитровская","station_id":"10.79","line_id":"10","lat":55.649158,"lng":37.743844},{"station_name":"Площадь Революции","line_name":"Арбатско-Покровская","station_id":"3.100","line_id":"3","lat":55.756741,"lng":37.62236},{"station_name":"Театральная","line_name":"Замоскворецкая","station_id":"2.99","line_id":"2","lat":55.758808,"lng":37.61768}]},"allow_messages":true,"site":{"id":"hh","name":"hh.ru"},"experience":{"id":"noExperience","name":"Нет опыта"},"schedule":{"id":"shift","name":"Сменный график"},"employment":{"id":"probation","name":"Стажировка"},"department":null,"contacts":null,"description":"<p><strong>Бариста-ученик в кофейню премиум сегмента</strong></p> <p><strong>Работай в Москве с удовольствием! Вкусная кофейня и должность баристы ждет!</strong></p> <p><strong>Вакансия бариста без опыта с обучением, с функциями кассира в сеть кафе</strong></p> <p><strong>Условия для бариста без опыта:</strong></p> <ol> <li> <p>Варианты графиков работы: 2/2, 5/2, 6/1</p> </li> <li> <p>Ставка за смену от 2200 руб.</p> </li> <li> <p>Работа В ЦЕНТРЕ МОСКВЫ или рядом с домом (подбираем индивидуально)!</p> </li> <li> <p>Курсы бариста - БЕСПЛАТНО!</p> </li> <li> <p>Питанием обеспечиваем бесплатно без вычетов!</p> </li> <li> <p>Помогаем с изготовлением медицинской книжки.</p> </li> <li> <p>Заработная плата выплачивается БЕЗ ЗАДЕРЖЕК 2 раза в месяц строго по ТК РФ. Отпуск, больничный, переработки – оплачиваются в соответствии с законодательством РФ.</p> </li> <li> <p>Стабильность работы и регулярность выплат – гарантированы законодательством РФ и трудовым договором.</p> </li> <li> <p>Есть премии!</p> </li> <li> <p>Алкоголь в кафе не продается!</p> </li> </ol> <p><strong>Обязанности: </strong></p> <ul> <li>Работа на автоматической кофе-машине по графикам 2/2, 5/2, 6/1</li> <li>Отпуск товара на кассе</li> </ul> <p><strong>Требования:</strong></p> <ul> <li> <p>Пунктуальность</p> </li> <li> <p>Аккуратность</p> </li> <li> <p>Грамотная русская речь</p> </li> <li> <p>Вежливость</p> </li> </ul> <p>Мы готовы обучать своих сотрудников. Однако, если у Вас есть опыт работы (на таких должностях как бариста, бариста-кассир, бармен, кофе-леди, официант, кассир, продавец), то это будет преимуществом.</p> <p><strong>Звоните уточнить детали и забронировать вакансию!<br />Мы работаем без выходных с 8 до 20 часов.</strong></p>","branded_description":null,"vacancy_constructor_template":null,"key_skills":[],"accept_handicapped":true,"accept_kids":false,"archived":false,"response_url":null,"specializations":[{"id":"29.588","name":"Другое","profarea_id":"29","profarea_name":"Рабочий персонал"},{"id":"4.734","name":"Другое","profarea_id":"4","profarea_name":"Административный персонал"},{"id":"15.750","name":"Другое","profarea_id":"15","profarea_name":"Начало карьеры, студенты"},{"id":"17.751","name":"Другое","profarea_id":"17","profarea_name":"Продажи"},{"id":"2.737","name":"Другое","profarea_id":"2","profarea_name":"Бухгалтерия, управленческий учет, финансы предприятия"},{"id":"22.757","name":"Другое","profarea_id":"22","profarea_name":"Туризм, гостиницы, рестораны"}],"code":null,"hidden":false,"quick_responses_allowed":false,"driver_license_types":[],"accept_incomplete_resumes":true,"employer":{"id":"5683314","name":"Брайт","url":"https://api.hh.ru/employers/5683314?host=hh.ru","alternate_url":"https://hh.ru/employer/5683314","logo_urls":{"240":"https://hhcdn.ru/employer-logo/3982704.png","90":"https://hhcdn.ru/employer-logo/3982703.png","original":"https://hhcdn.ru/employer-logo-original/885501.png"},"vacancies_url":"https://api.hh.ru/vacancies?employer_id=5683314&host=hh.ru","trusted":true},"published_at":"2021-09-22T12:35:23+0300","created_at":"2021-09-22T12:35:23+0300","negotiations_url":null,"suitable_resumes_url":null,"apply_alternate_url":"https://hh.ru/applicant/vacancy_response?vacancyId=47763742","has_test":false,"test":null,"alternate_url":"https://hh.ru/vacancy/47763742","working_days":[],"working_time_intervals":[],"working_time_modes":[],"accept_temporary":true}