{"id":"47957002","premium":false,"billing_type":{"id":"standard","name":"Стандарт"},"relations":[],"name":"Секретарь-делопроизводитель","insider_interview":null,"response_letter_required":false,"area":{"id":"1","name":"Москва","url":"https://api.hh.ru/areas/1?host=hh.ru"},"salary":{"from":80000,"to":null,"currency":"RUR","gross":true},"type":{"id":"anonymous","name":"Анонимная"},"address":null,"allow_messages":true,"site":{"id":"hh","name":"hh.ru"},"experience":{"id":"between1And3","name":"От 1 года до 3 лет"},"schedule":{"id":"fullDay","name":"Полный день"},"employment":{"id":"full","name":"Полная занятость"},"department":null,"contacts":null,"description":"<p><strong>Обязанности:</strong></p> <ul> <li>Полная административная поддержка руководителя, ведение личного календаря</li> <li>Подготовка и организация приема посетителей, встреч и совещаний (сбор необходимых материалов, оповещение участников о времени и месте проведения и повестке совещания, оформление протоколов по результатам проведения совещания)</li> <li>Организация документооборота (работа с корреспонденцией, регистрация и обработка входящей и исходящей документации</li> <li>Travel-поддержка руководителя, организация поездок и командировок (заказ билетов, бронирование гостиницы)</li> <li>Доведение до руководителей подразделений указаний, распоряжений, поручений руководителя, контроль их исполнения точно в срок;</li> <li>Заказ канцтоваров, офисного оборудования и расходных материалов</li> <li>Выполнение личных поручений руководителя.</li> </ul> <p><strong>Требования:</strong></p> <ul> <li>Высшее образование</li> <li>Отличное владение офисной техникой</li> <li>Знание основ делового этикета</li> <li>Опыт работы на аналогичной позиции с первыми лицами компании не менее 2-х лет</li> <li>Уверенный пользователь ПК</li> <li>Личные качества: коммуникабельность,стрессоустойчивость, аккуратность и пунктуальность</li> </ul> <p><strong>Условия:</strong></p> <ul> <li>Работа в крупном холдинге (телекоммуникации)</li> <li>Офис в 15 мин. от м. Алексеевская, ж/д ст. Маленковская</li> <li>Режим работы: 5/2 с 09:00 до 18:00</li> <li>Оформление в соответствии с ТК РФ</li> <li>Уровень заработной платы обсуждается с успешными кандидатом</li> <li>ДМС</li> </ul> <p> </p>","branded_description":null,"vacancy_constructor_template":null,"key_skills":[{"name":"Организация встреч"},{"name":"Делопроизводство"},{"name":"Протоколирование"},{"name":"Организация деловых поездок"},{"name":"Административная поддержка руководителя"}],"accept_handicapped":false,"accept_kids":false,"archived":false,"response_url":null,"specializations":[{"id":"4.429","name":"Делопроизводство","profarea_id":"4","profarea_name":"Административный персонал"}],"code":null,"hidden":false,"quick_responses_allowed":false,"driver_license_types":[],"accept_incomplete_resumes":false,"employer":{"name":"Крупный холдинг (телекоммуникации)приглашает к сотрудничеству Секретаря генерального директора"},"published_at":"2021-09-14T23:08:49+0300","created_at":"2021-09-14T23:08:49+0300","negotiations_url":null,"suitable_resumes_url":null,"apply_alternate_url":"https://hh.ru/applicant/vacancy_response?vacancyId=47957002","has_test":false,"test":null,"alternate_url":"https://hh.ru/vacancy/47957002","working_days":[],"working_time_intervals":[],"working_time_modes":[],"accept_temporary":false}