{"id":"48034887","premium":false,"billing_type":{"id":"standard_plus","name":"Стандарт плюс"},"relations":[],"name":"Продавец-консультант в бутик YANA на Мальдивах","insider_interview":null,"response_letter_required":false,"area":{"id":"1","name":"Москва","url":"https://api.hh.ru/areas/1?host=hh.ru"},"salary":{"from":100000,"to":null,"currency":"RUR","gross":true},"type":{"id":"open","name":"Открытая"},"address":null,"allow_messages":true,"site":{"id":"hh","name":"hh.ru"},"experience":{"id":"between3And6","name":"От 3 до 6 лет"},"schedule":{"id":"fullDay","name":"Полный день"},"employment":{"id":"full","name":"Полная занятость"},"department":null,"contacts":null,"description":"<p>Модный дом <strong>YANA </strong>основан дизайнером Яной Расковаловой в 2011 году и на данный момент представляет следующие направления:</p> <p><strong>Yana Jewellery</strong> – эксклюзивные ювелирные изделия</p> <p><strong>Yana Dress</strong> – одежда и аксессуары Haute Couture</p> <p><strong>Like Yana</strong> – повседневная молодежная линия одежды, а также ювелирные украшения из серебра</p> <p><strong>Продавец-консультант в бутик YANA на Мальдивах</strong></p> <p><em>Обязанности:</em></p> <ul> <li>Выполнение плана по продажам</li> <li>Обеспечение высокого уровня обслуживания клиентов</li> <li>Подготовка товара и торгового зала для осуществления процесса продаж, участие в инвентаризациях</li> <li>Знание бренда, коллекций, подбор клиенту полноценного образа</li> <li>Ведение клиентской базы: постоянная коммуникация с клиентами и развитие долгосрочных отношений с ними</li> <li>Выполнение кассовых операций, ведение кассовых документов</li> <li>Ведение необходимой отчетности</li> <li>Решение организационных вопросов с администрацией отеля</li> </ul> <p><em>Требования:</em></p> <ul> <li>Высшее образование</li> <li>Свободный английский (знание других иностранных языков является плюсом)</li> <li>Опыт работы в продажах (сегмент luxury) от 3-х лет</li> <li>Высокий уровень владения техниками продаж</li> <li>Уверенные навыки презентации, грамотная речь, коммуникабельность</li> <li>Стрессоустойчивость</li> <li>Ответственность, нацеленность на результат</li> </ul> <p><em>Условия:</em></p> <ul> <li>График работы 6/1, 8-часовой рабочий день</li> <li>Оклад + % от продаж</li> <li>Официальное оформление, социальные гарантии</li> <li>Бутик расположен в отеле One&amp;Only на Мальдивах</li> <li>Компания обеспечивает всеми необходимыми документами и разрешениями, а также проживанием и питанием</li> </ul>","branded_description":null,"vacancy_constructor_template":null,"key_skills":[{"name":"Грамотная речь"},{"name":"Работа в команде"},{"name":"Пользователь ПК"},{"name":"Английский язык"},{"name":"Навыки продаж"}],"accept_handicapped":false,"accept_kids":false,"archived":false,"response_url":null,"specializations":[{"id":"11.157","name":"Мода","profarea_id":"11","profarea_name":"Искусство, развлечения, масс-медиа"},{"id":"17.256","name":"Розничная торговля","profarea_id":"17","profarea_name":"Продажи"},{"id":"17.440","name":"Текстиль, Одежда, Обувь","profarea_id":"17","profarea_name":"Продажи"}],"code":null,"hidden":false,"quick_responses_allowed":false,"driver_license_types":[],"accept_incomplete_resumes":false,"employer":{"id":"1763932","name":"Yana","url":"https://api.hh.ru/employers/1763932?host=hh.ru","alternate_url":"https://hh.ru/employer/1763932","logo_urls":{"original":"https://hhcdn.ru/employer-logo-original/250866.jpg","240":"https://hhcdn.ru/employer-logo/1446138.jpeg","90":"https://hhcdn.ru/employer-logo/1446137.jpeg"},"vacancies_url":"https://api.hh.ru/vacancies?employer_id=1763932&host=hh.ru","trusted":true},"published_at":"2021-09-20T09:39:01+0300","created_at":"2021-09-20T09:39:01+0300","negotiations_url":null,"suitable_resumes_url":null,"apply_alternate_url":"https://hh.ru/applicant/vacancy_response?vacancyId=48034887","has_test":false,"test":null,"alternate_url":"https://hh.ru/vacancy/48034887","working_days":[],"working_time_intervals":[],"working_time_modes":[],"accept_temporary":false}