{"id":"48150910","premium":false,"billing_type":{"id":"standard","name":"Стандарт"},"relations":[],"name":"Специалист по документообороту","insider_interview":null,"response_letter_required":false,"area":{"id":"1","name":"Москва","url":"https://api.hh.ru/areas/1?host=hh.ru"},"salary":{"from":null,"to":60000,"currency":"RUR","gross":false},"type":{"id":"open","name":"Открытая"},"address":null,"allow_messages":true,"site":{"id":"hh","name":"hh.ru"},"experience":{"id":"noExperience","name":"Нет опыта"},"schedule":{"id":"shift","name":"Сменный график"},"employment":{"id":"full","name":"Полная занятость"},"department":{"id":"80-80-bank","name":" Альфа-Банк"},"contacts":null,"description":"<p><strong>Чем предстоит заниматься:</strong></p> <ul> <li>Подготавливать клиентские досье для отдела доставки банковских продуктов и партнерских каналов.</li> <li>Проверять клиенскихедокументы для последующей сдачи в архив Банка</li> <li>Решать вопросы по неработоспособности эмбоссера ( подключение процессингово центра, вызов инженера и пр.)</li> <li>Ежедневно вести расчеы по остаткам карт, заказывать карты, контролировать и уничтожать карты, аудит карт</li> <li>Контролировать остатки бреднированных конвертов для доставки карт</li> <li>Взаимодействовать с кредитно - кассовыми офисами для подготовки карт, с отделом доставки банковских продуктов для разработки мероприятий по предотвращению потерь клиентских документов, своевременной сдачи документов и проработки ошибок</li> </ul> <p><strong>Наши пожелания к кандидатам:</strong></p> <ul> <li>Высшее/ незаконченное высшее образование (экономика, финансы, банковское дело)</li> <li>Опытный пользователь компьютерных программ MS OFFICE (Excel, Word, Power Point)</li> <li>Приветствуется опыт кассовой работы в кредитных организациях</li> <li>Наличие положительных рекомендаций с предыдущих мест работы</li> <li>Высокая ориентация на результат, аккуратность, грамотная речь</li> </ul> <p><strong>Условия:</strong></p> <ul> <li>.м. Владыкино</li> <li>Графк работы ночные смены 2 через 2 с 19.00 до 7.00 или с 20.00 до 8.00</li> <li>Стабильный и прозрачный доход (оклад + ежемесячная премия)</li> <li>Регулярное проведение тренингов, вебинаров, бизнес-игр</li> <li>Доступ к бесплатным корпоративным библиотекам Альпины, МИФа и бизнес - изданий, скидки на курсы иностранных языков</li> <li>Карьерный рост</li> <li>Забота о здоровье программа ДМС, куда входит стоматология и обслуживание в лучших клиниках города, скидки на абонементы в фитнес-клубы, неформальные спортивные сообщества</li> <li>Возможности для разнообразного досуга: скидки на услуги туристических агентств, продукты питания, в рестораны и бары, в магазины и салоны красоты</li> <li>Предложения от банка только для сотрудников: ипотека на льготных условиях, а также льготные условия обслуживания на карты Cash Back и другие</li> </ul>","branded_description":"\n<style>\n.tmpl_hh_wrapper p,\n.tmpl_hh_wrapper a,\n.tmpl_hh_wrapper img,\n.tmpl_hh_wrapper ol,\n.tmpl_hh_wrapper ul,\n.tmpl_hh_wrapper li {\n    margin: 0;\n    padding: 0;\n    border: 0;\n    font-size: 100%;\n    font: inherit;\n    vertical-align: baseline;\n}\n\n.hht-vacancydescription {\n    padding: 0px;\n}\n\n.tmpl_hh_wrapper .l-cell,\n.tmpl_hh_wrapper .l-paddings {\n    padding: 0px !important;\n}\n\n.tmpl_hh_wrapper .b-vacancy-desc-wrapper {\n    margin-top: 0px !important;    \n}\n\n.tmpl_hh_wrapper .b-vacancy-desc {\n    overflow: visible !important;\n    line-height: inherit;\n}\n\n.tmpl_hh_content ol li b,\n.tmpl_hh_content ol li strong,\n.tmpl_hh_content ol li p b,\n.tmpl_hh_content ol li p strong,\n.tmpl_hh_content ul li b,\n.tmpl_hh_content ul li strong,\n.tmpl_hh_content ul li p b,\n.tmpl_hh_content ul li p strong {\n    font-weight: normal;\n    font-size: inherit !important;\n    color: inherit !important;\n    margin: 0 !important;\n    text-transform: none;\n    line-height: inherit;\n}\n\n.tmpl_hh_content ol li p,\n.tmpl_hh_content ul li p {\n    font-weight: normal;\n    margin: 0;\n}\n\n.tmpl_hh_content p b,\n.tmpl_hh_content p strong {\n    display: inline;\n    margin: 0 0 0;\n}\n\n.tmpl_hh_wrapper {\n    width: 100%;\n    margin: 0 auto;\n    max-width: 690px;\n    position: relative;\n    word-break: normal;\n    color: #333333;\n    overflow: hidden;\n    font-family: 'Verdana';\n    font-size: 16px;\n    line-height: 16px;\n    border-bottom: 47px solid #eb3124;\n}\n\n.tmpl_hh_wrapper img {\n    width: 100%;\n    display: block;\n}\n\n.tmpl_hh_content {\n    padding: 36px 100px 60px;\n    position: relative;\n    z-index: 1;\n}\n\n.tmpl_hh_content p:first-child,\n.tmpl_hh_content>strong:first-child,\n.tmpl_hh_content div>strong:first-child {\n    margin-top: 0 !important;\n}\n\n.tmpl_hh_content p,\n.tmpl_hh_content b,\n.tmpl_hh_content strong {\n   margin: 36px 0 26px;\n}\n\n.tmpl_hh_content b, \n.tmpl_hh_content strong {\n    display: inline-block;\n    font-weight: bold;\n    font-size: 16px;\n    line-height: 16px;\n    color: #eb3124;\n}\n\n.tmpl_hh_content ol, \n.tmpl_hh_content ul {\n    list-style: none !important;\n    margin-left: 16px;\n}\n\n.tmpl_hh_content ol {\n    counter-reset: list_counter;\n}\n\n.tmpl_hh_content li {\n    position: relative;\n    margin-bottom: 16px;\n}\n\n.tmpl_hh_content ul ul,\n.tmpl_hh_content ul ol,\n.tmpl_hh_content ol ol,\n.tmpl_hh_content ol ul {\n    margin-top: 16px;\n}\n\n.tmpl_hh_content ol>li {\n    counter-increment: list_counter;    \n}\n\n.tmpl_hh_content li:before {\n    position: absolute;\n    left: -16px;\n    top: 0;\n}\n\n.tmpl_hh_content ul>li:before {\n    content: \"\\2022\";\n}\n\n.tmpl_hh_content ol>li:before {\n    content: counter(list_counter)'.';\n    left: auto;\n    right: 100%;\n    margin-right: 2px;\n}\n\n.tmpl_hh_flex {\n    display: -webkit-box;\n    display: -ms-flexbox;\n    display: flex;\n    -webkit-box-pack: justify;\n    -ms-flex-pack: justify;\n    justify-content: space-between;\n    -ms-flex-wrap: wrap;\n    flex-wrap: wrap;\n}\n\n.tmpl_hh_header {\n    position: relative;\n}\n\na.tmpl_hh_button {\n    display: inline-block;\n    background: #eb3124;\n    color: #fff;\n    margin: 50px 0 0;\n    font-size: 16px;\n    line-height: 20px;\n    padding: 10px 24px 12px 27px;\n    border-radius: 5px;\n}\n\n\n@media screen and (max-width: 699px) {\n    .tmpl_hh_content {\n        padding: 36px 6% 40px;\n    }\n\n    a.tmpl_hh_button {\n        margin: 29px 0 0;\n    }\n}\n\n</style>\n\n<script>\n//\ndocument.addEventListener('DOMContentLoaded', function(){\n   var headerButton = document.querySelector('.tmpl_hh_button');\n    headerButton.addEventListener('click', function(e){\n        e.preventDefault();\n        var vacancyBlock = document.querySelector('.bloko-button_secondary');\n        if (vacancyBlock !== null) vacancyBlock.scrollIntoView({behavior: \"smooth\"});\n    });\n}); \n//\n</script>\n\n<div class=\"tmpl_hh_wrapper\">\n    <div class=\"tmpl_hh_header\">\n        <img src=\"https://hhcdn.ru/ichameleon/163783.jpg\" alt=\"\">\n    </div>\n    <div class=\"tmpl_hh_content\">\n       <p><strong>Чем предстоит заниматься:</strong></p> <ul> <li>Подготавливать клиентские досье для отдела доставки банковских продуктов и партнерских каналов.</li> <li>Проверять клиенскихедокументы для последующей сдачи в архив Банка</li> <li>Решать вопросы по неработоспособности эмбоссера ( подключение процессингово центра, вызов инженера и пр.)</li> <li>Ежедневно вести расчеы по остаткам карт, заказывать карты, контролировать и уничтожать карты, аудит карт</li> <li>Контролировать остатки бреднированных конвертов для доставки карт</li> <li>Взаимодействовать с кредитно - кассовыми офисами для подготовки карт, с отделом доставки банковских продуктов для разработки мероприятий по предотвращению потерь клиентских документов, своевременной сдачи документов и проработки ошибок</li> </ul> <p><strong>Наши пожелания к кандидатам:</strong></p> <ul> <li>Высшее/ незаконченное высшее образование (экономика, финансы, банковское дело)</li> <li>Опытный пользователь компьютерных программ MS OFFICE (Excel, Word, Power Point)</li> <li>Приветствуется опыт кассовой работы в кредитных организациях</li> <li>Наличие положительных рекомендаций с предыдущих мест работы</li> <li>Высокая ориентация на результат, аккуратность, грамотная речь</li> </ul> <p><strong>Условия:</strong></p> <ul> <li>.м. Владыкино</li> <li>Графк работы ночные смены 2 через 2 с 19.00 до 7.00 или с 20.00 до 8.00</li> <li>Стабильный и прозрачный доход (оклад + ежемесячная премия)</li> <li>Регулярное проведение тренингов, вебинаров, бизнес-игр</li> <li>Доступ к бесплатным корпоративным библиотекам Альпины, МИФа и бизнес - изданий, скидки на курсы иностранных языков</li> <li>Карьерный рост</li> <li>Забота о здоровье программа ДМС, куда входит стоматология и обслуживание в лучших клиниках города, скидки на абонементы в фитнес-клубы, неформальные спортивные сообщества</li> <li>Возможности для разнообразного досуга: скидки на услуги туристических агентств, продукты питания, в рестораны и бары, в магазины и салоны красоты</li> <li>Предложения от банка только для сотрудников: ипотека на льготных условиях, а также льготные условия обслуживания на карты Cash Back и другие</li> </ul><a class=\"tmpl_hh_button\" href=\"#\">Отправить резюме!</a>\n    </div>\n    \n</div>\n\n","vacancy_constructor_template":null,"key_skills":[{"name":"Грамотность"},{"name":"Грамотная речь"},{"name":"Навыки презентации"},{"name":"Управление отношениями с клиентами"},{"name":"MS PowerPoint"}],"accept_handicapped":false,"accept_kids":false,"archived":false,"response_url":null,"specializations":[{"id":"5.126","name":"Кредиты","profarea_id":"5","profarea_name":"Банки, инвестиции, лизинг"},{"id":"5.735","name":"Другое","profarea_id":"5","profarea_name":"Банки, инвестиции, лизинг"},{"id":"5.177","name":"Начальный уровень, Мало опыта","profarea_id":"5","profarea_name":"Банки, инвестиции, лизинг"},{"id":"5.51","name":"Внутренние операции (Back Office)","profarea_id":"5","profarea_name":"Банки, инвестиции, лизинг"},{"id":"5.106","name":"Коммерческий банк","profarea_id":"5","profarea_name":"Банки, инвестиции, лизинг"}],"code":null,"hidden":false,"quick_responses_allowed":false,"driver_license_types":[],"accept_incomplete_resumes":false,"employer":{"id":"80","name":"Альфа-Банк","url":"https://api.hh.ru/employers/80?host=hh.ru","alternate_url":"https://hh.ru/employer/80","logo_urls":{"original":"https://hhcdn.ru/employer-logo-original/663873.png","240":"https://hhcdn.ru/employer-logo/3096625.png","90":"https://hhcdn.ru/employer-logo/3096624.png"},"vacancies_url":"https://api.hh.ru/vacancies?employer_id=80&host=hh.ru","trusted":true},"published_at":"2021-09-21T21:12:07+0300","created_at":"2021-09-21T21:12:07+0300","negotiations_url":null,"suitable_resumes_url":null,"apply_alternate_url":"https://hh.ru/applicant/vacancy_response?vacancyId=48150910","has_test":false,"test":null,"alternate_url":"https://hh.ru/vacancy/48150910","working_days":[],"working_time_intervals":[],"working_time_modes":[],"accept_temporary":false}